pyurify/__init__.py
pyurify/cli.py
pyurify/logger.py
pyurify/pcov.py
pyurify/purification.py
pyurify/slicer.py
pyurify-0.0.1.dist-info/licenses/LICENSE
pyurify-0.0.1.dist-info/METADATA
pyurify-0.0.1.dist-info/WHEEL
pyurify-0.0.1.dist-info/entry_points.txt
pyurify-0.0.1.dist-info/top_level.txt
pyurify-0.0.1.dist-info/RECORD
