Metadata-Version: 2.4
Name: pyurify
Version: 0.0.1
Summary: Pyurify: Purifying Python Tests for Precise Fault Localization
Author-email: Marius Smytzek <marius.smytzek@cispa.de>
License:                                  Apache License
Project-URL: Homepage, https://github.com/smythi93/pyurify/
Project-URL: Bug Tracker, https://github.com/smythi93/pyurify/issues
Classifier: Intended Audience :: Science/Research
Classifier: Programming Language :: Python :: 3.10
Classifier: Programming Language :: Python :: 3.11
Classifier: Programming Language :: Python :: 3.12
Classifier: Programming Language :: Python :: 3.13
Classifier: Programming Language :: Python :: 3.14
Classifier: License :: OSI Approved :: Apache Software License
Classifier: Topic :: Scientific/Engineering
Classifier: Topic :: Software Development :: Testing
Requires-Python: >=3.10
License-File: LICENSE
Provides-Extra: test
Requires-Dist: pytest>=9.0.2; extra == "test"
Requires-Dist: pytest-html>=4.2.0; extra == "test"
Requires-Dist: pytest-cov>=7.0.0; extra == "test"
Dynamic: license-file
